{"cameraMode":{"drawMode":0,"name":"Shaded","section":"Shading Mode"},"sceneLighting":true,"audioPlay":false,"sceneViewState":{"showFog":true,"showMaterialUpdate":false,"showSkybox":true,"showFlares":true,"showImageEffects":true,"showParticleSystems":true},"in2DMode":false,"pivot":{"x":8.69709587097168,"y":-0.3474693298339844,"z":10.233142852783204},"rotation":{"x":-0.21086886525154115,"y":-0.7434064745903015,"z":0.27373355627059939,"w":-0.5726773738861084},"size":32.694095611572269,"orthographic":false}